zscaler_mcp/__init__.py
zscaler_mcp/client.py
zscaler_mcp/server.py
zscaler_mcp/services.py
zscaler_mcp/common/__init__.py
zscaler_mcp/common/elicitation.py
zscaler_mcp/common/logging.py
zscaler_mcp/common/tool_helpers.py
zscaler_mcp/tools/__init__.py
zscaler_mcp/tools/easm/__init__.py
zscaler_mcp/tools/easm/findings.py
zscaler_mcp/tools/easm/lookalike_domains.py
zscaler_mcp/tools/easm/organizations.py
zscaler_mcp/tools/zcc/__init__.py
zscaler_mcp/tools/zcc/download_devices.py
zscaler_mcp/tools/zcc/list_devices.py
zscaler_mcp/tools/zcc/list_forwarding_profiles.py
zscaler_mcp/tools/zcc/list_trusted_networks.py
zscaler_mcp/tools/zdx/__init__.py
zscaler_mcp/tools/zdx/active_devices.py
zscaler_mcp/tools/zdx/administration.py
zscaler_mcp/tools/zdx/get_application_metric.py
zscaler_mcp/tools/zdx/get_application_score.py
zscaler_mcp/tools/zdx/get_application_user.py
zscaler_mcp/tools/zdx/list_alerts.py
zscaler_mcp/tools/zdx/list_applications.py
zscaler_mcp/tools/zdx/list_deep_traces.py
zscaler_mcp/tools/zdx/list_historical_alerts.py
zscaler_mcp/tools/zdx/list_software_inventory.py
zscaler_mcp/tools/zia/__init__.py
zscaler_mcp/tools/zia/activation.py
zscaler_mcp/tools/zia/atp_malicious_urls.py
zscaler_mcp/tools/zia/auth_exempt_urls.py
zscaler_mcp/tools/zia/cloud_applications.py
zscaler_mcp/tools/zia/cloud_firewall_rules.py
zscaler_mcp/tools/zia/geo_search.py
zscaler_mcp/tools/zia/get_sandbox_info.py
zscaler_mcp/tools/zia/gre_ranges.py
zscaler_mcp/tools/zia/gre_tunnels.py
zscaler_mcp/tools/zia/ip_destination_groups.py
zscaler_mcp/tools/zia/ip_source_groups.py
zscaler_mcp/tools/zia/list_dlp_dictionaries.py
zscaler_mcp/tools/zia/list_dlp_engines.py
zscaler_mcp/tools/zia/list_user_departments.py
zscaler_mcp/tools/zia/list_user_groups.py
zscaler_mcp/tools/zia/list_users.py
zscaler_mcp/tools/zia/location_management.py
zscaler_mcp/tools/zia/network_app_groups.py
zscaler_mcp/tools/zia/rule_labels.py
zscaler_mcp/tools/zia/ssl_inspection.py
zscaler_mcp/tools/zia/static_ips.py
zscaler_mcp-0.6.1.dist-info/licenses/LICENSE
zscaler_mcp-0.6.1.dist-info/METADATA
zscaler_mcp-0.6.1.dist-info/WHEEL
zscaler_mcp-0.6.1.dist-info/entry_points.txt
zscaler_mcp-0.6.1.dist-info/top_level.txt
zscaler_mcp-0.6.1.dist-info/RECORD
