Metadata-Version: 2.4
Name: zscaler-mcp
Version: 0.6.1
Summary: Official Zscaler Integrations MCP Server
Author-email: "Zscaler, Inc." <devrel@zscaler.com>
License-Expression: MIT
Classifier: Development Status :: 3 - Alpha
Classifier: Intended Audience :: Developers
Classifier: Programming Language :: Python :: 3
Classifier: Programming Language :: Python :: 3.11
Classifier: Programming Language :: Python :: 3.12
Classifier: Programming Language :: Python :: 3.13
Requires-Python: <4.0,>=3.11
License-File: LICENSE
Requires-Dist: zscaler-sdk-python
Requires-Dist: mcp[cli]>=1.23.0
Requires-Dist: fastmcp>=2.13.0
Requires-Dist: python-dotenv
Requires-Dist: click
Requires-Dist: uvicorn
Requires-Dist: fastapi
Requires-Dist: pycountry
Requires-Dist: authlib>=1.6.5
Requires-Dist: cryptography>=46.0.1
Requires-Dist: huggingface-hub>=0.35.0
Requires-Dist: jiter>=0.11.0
Requires-Dist: langsmith>=0.4.28
Requires-Dist: openai>=1.107.3
Requires-Dist: posthog>=6.7.5
Requires-Dist: pydantic>=2.11.9
Requires-Dist: starlette>=0.49.1
Requires-Dist: zstandard>=0.25.0
Requires-Dist: package-name>=0.1
Requires-Dist: urllib3>=2.6.0
Requires-Dist: werkzeug>=3.1.4
Provides-Extra: dev
Requires-Dist: pytest; extra == "dev"
Requires-Dist: pytest-cov; extra == "dev"
Requires-Dist: black; extra == "dev"
Requires-Dist: mypy; extra == "dev"
Requires-Dist: ipython; extra == "dev"
Requires-Dist: ruff; extra == "dev"
Requires-Dist: pycountry; extra == "dev"
Requires-Dist: pytest-asyncio>=0.21.0; extra == "dev"
Requires-Dist: langchain-openai>=0.3.28; extra == "dev"
Requires-Dist: mcp-use[search]>=1.3.7; extra == "dev"
Provides-Extra: docs
Requires-Dist: sphinx>=7.3.5; extra == "docs"
Requires-Dist: furo>=2024.1.29; extra == "docs"
Requires-Dist: myst-parser>=2.0.0; extra == "docs"
Requires-Dist: sphinx-rtd-theme>=2.0.0; extra == "docs"
Requires-Dist: sphinx-autodoc-typehints>=1.24.0; extra == "docs"
Requires-Dist: sphinx-copybutton>=0.5.0; extra == "docs"
Requires-Dist: sphinx-design>=0.5.0; extra == "docs"
Dynamic: license-file
